madframe/__init__.py
madframe/autofill.py
madframe/bindings.py
madframe/command.py
madframe/options.py
madframe/perpetuate.py
madframe/routines.py
madframe/setup.py
madframe-0.0.1.dist-info/METADATA
madframe-0.0.1.dist-info/WHEEL
madframe-0.0.1.dist-info/entry_points.txt
madframe-0.0.1.dist-info/top_level.txt
madframe-0.0.1.dist-info/RECORD
